__init__.py
cmdlogtime.py
cmdlogtime-0.0.4.dist-info/LICENSE
cmdlogtime-0.0.4.dist-info/METADATA
cmdlogtime-0.0.4.dist-info/WHEEL
cmdlogtime-0.0.4.dist-info/top_level.txt
cmdlogtime-0.0.4.dist-info/RECORD
