Metadata-Version: 2.1
Name: cmdlogtime
Version: 0.0.4
Summary: This package does command line processing, allows for logging, and keeps track of start, end, and elapsed time, along with a bunch of other stuff.
Author-email: Ron Stewart <rstewart@morgridge.org>
Project-URL: Repository, https://github.com/stewart-lab/cmdlogtime
License-File: LICENSE
